LICENSE
MANIFEST.in
README.md
pyproject.toml
setup.py
mercury/explainability/__init__.py
mercury/explainability/create_tutorials.py
mercury/explainability/pyspark_utils.py
mercury/explainability/explainers/__init__.py
mercury/explainability/explainers/_dummy_alibi_explainers.py
mercury/explainability/explainers/ale.py
mercury/explainability/explainers/anchors.py
mercury/explainability/explainers/cf_strategies.py
mercury/explainability/explainers/clustering_tree_explainer.py
mercury/explainability/explainers/counter_fact_basic.py
mercury/explainability/explainers/counter_fact_importance.py
mercury/explainability/explainers/explainer.py
mercury/explainability/explainers/partial_dependence.py
mercury/explainability/explainers/shuffle_importance.py
mercury/explainability/explainers/_tree_splitters/__init__.py
mercury/explainability/explainers/_tree_splitters/cut_finder.c
mercury/explainability/explainers/_tree_splitters/cut_finder.pyx
mercury/explainability/explanations/__init__.py
mercury/explainability/explanations/anchors.py
mercury/explainability/explanations/clustering_tree_explanation.py
mercury/explainability/explanations/counter_factual.py
mercury/explainability/explanations/partial_dependence.py
mercury/explainability/explanations/shuffle_importance.py
mercury/explainability/tutorials/BasicTutorial.ipynb
mercury/explainability/tutorials/BasicTutorial_colab.ipynb
mercury/explainability/tutorials/tutorial_clustering_tree_explainer.ipynb
mercury/explainability/tutorials/tutorial_counterfactual_basic_explainer.ipynb
mercury/explainability/tutorials/tutorial_counterfactual_basic_explainer_higher_dim.ipynb
mercury/explainability/tutorials/tutorial_partial_dependence_plots.ipynb
mercury/explainability/tutorials/tutorial_shuffle_importance_explainer.ipynb
mercury/explainability/tutorials/data/credit/UCI_Credit_card.csv
mercury/explainability/tutorials/data/winequality/winequality-red.csv
mercury/explainability/tutorials/data/winequality/winequality-white.csv
mercury_explainability.egg-info/PKG-INFO
mercury_explainability.egg-info/SOURCES.txt
mercury_explainability.egg-info/dependency_links.txt
mercury_explainability.egg-info/requires.txt
mercury_explainability.egg-info/top_level.txt