Metadata-Version: 2.1
Name: mercury-explainability
Version: 1.1.4
Summary: Mercury's explainability is a library with implementations of different state-of-the-art methods in the field of explainability
Author-email: Mercury Team <mercury.group@bbva.com>
Project-URL: Homepage, https://github.com/BBVA/mercury-explainability
Project-URL: Bug Tracker, https://github.com/BBVA/mercury-explainability/issues
Classifier: Programming Language :: Python :: 3
Classifier: License :: OSI Approved :: Apache Software License
Classifier: Operating System :: OS Independent
Requires-Python: >=3.7
Provides-Extra: dev
Provides-Extra: doc
License-File: LICENSE
